procrustus_indexer/__init__.py
procrustus_indexer/indexer.py
procrustus_indexer/indexer_builder.py
procrustus_indexer/parsers/__init__.py
procrustus_indexer/parsers/json_parser.py
procrustus_indexer/parsers/parser.py
procrustus_indexer-2.0.0.dist-info/METADATA
procrustus_indexer-2.0.0.dist-info/WHEEL
procrustus_indexer-2.0.0.dist-info/RECORD
