Metadata-Version: 2.3
Name: procrustus-indexer
Version: 2.0.0
Summary: 
Author: Rob Zeeman
Author-email: rob.zeeman@di.huc.knaw.nl
Requires-Python: >=3.13
Classifier: Programming Language :: Python :: 3
Classifier: Programming Language :: Python :: 3.13
Requires-Dist: elasticsearch (>=8.17.2,<9.0.0)
Requires-Dist: jmespath (>=1.0.1,<2.0.0)
Requires-Dist: pytest (>=8.3.5,<9.0.0)
